.VERSION
AUTHORS.rst
CONTRIBUTING.rst
HISTORY.rst
LICENSE
MANIFEST.in
Pipfile
Pipfile.lock
README.rst
USAGE.rst
dev-requirements.txt
requirements.txt
setup.cfg
setup.py
docs/Makefile
docs/authors.rst
docs/conf.py
docs/contributing.rst
docs/history.rst
docs/index.rst
docs/installation.rst
docs/modules.rst
docs/readme.rst
docs/terraformtestinglib.rst
docs/usage.rst
terraformtestinglib/.VERSION
terraformtestinglib/AUTHORS.rst
terraformtestinglib/CONTRIBUTING.rst
terraformtestinglib/HISTORY.rst
terraformtestinglib/LICENSE
terraformtestinglib/Pipfile
terraformtestinglib/Pipfile.lock
terraformtestinglib/README.rst
terraformtestinglib/USAGE.rst
terraformtestinglib/__init__.py
terraformtestinglib/_version.py
terraformtestinglib/configuration.py
terraformtestinglib/dev-requirements.txt
terraformtestinglib/requirements.txt
terraformtestinglib/terraformtestinglib.py
terraformtestinglib/terraformtestinglibexceptions.py
terraformtestinglib.egg-info/PKG-INFO
terraformtestinglib.egg-info/SOURCES.txt
terraformtestinglib.egg-info/dependency_links.txt
terraformtestinglib.egg-info/not-zip-safe
terraformtestinglib.egg-info/requires.txt
terraformtestinglib.egg-info/top_level.txt
terraformtestinglib/linting/__init__.py
terraformtestinglib/linting/linting.py
terraformtestinglib/testing/__init__.py
terraformtestinglib/testing/testing.py
terraformtestinglib/utils/__init__.py
terraformtestinglib/utils/errortypes.py
terraformtestinglib/utils/utils.py