Metadata-Version: 2.1
Name: terraformtestinglib
Version: 1.4.7
Summary: A library implementing linting and testing of terraform resources based on a provided rule set.
Home-page: https://github.com/schubergphilis/terraformtestinglib.git
Author: Costas Tyfoxylos
Author-email: ctyfoxylos@schubergphilis.com
License: MIT
Keywords: terraformtestinglib terraform lint test
Platform: UNKNOWN
Classifier: Development Status :: 4 - Beta
Classifier: Intended Audience :: Developers
Classifier: License :: OSI Approved :: MIT License
Classifier: Natural Language :: English
Classifier: Programming Language :: Python :: 3.7
License-File: LICENSE
License-File: AUTHORS.rst
